causaleffect/__init__.py
causaleffect/graph.py
causaleffect/id.py
causaleffect/probability.py
causaleffect-0.0.2.dist-info/METADATA
causaleffect-0.0.2.dist-info/WHEEL
causaleffect-0.0.2.dist-info/top_level.txt
causaleffect-0.0.2.dist-info/RECORD
