Metadata-Version: 2.1
Name: causaleffect
Version: 0.0.2
Summary: Computing causal effects
Home-page: https://github.com/pedemonte96/causaleffect
Author: Martí Pedemonte
Author-email: pedemonte96@gmail.com
License: UNKNOWN
Keywords: causaleffect,causality,causation,identifiability,identification,graph
Platform: UNKNOWN
Classifier: Development Status :: 3 - Alpha
Classifier: Intended Audience :: Science/Research
Classifier: Programming Language :: Python :: 3
Classifier: Operating System :: Microsoft :: Windows
Requires-Python: >=3.7
Requires-Dist: numpy (>=1.15.1)
Requires-Dist: python-igraph (>=0.8.3)
